README.md
setup.py
openhanzi/__init__.py
openhanzi.egg-info/PKG-INFO
openhanzi.egg-info/SOURCES.txt
openhanzi.egg-info/dependency_links.txt
openhanzi.egg-info/top_level.txt