Metadata-Version: 2.1
Name: openhanzi
Version: 0.1.1
Summary: A hanzi processing package
Home-page: 
Author: koshinryuu
License: Apache
Platform: UNKNOWN
